{
  "id": "2025-11-28-13",
  "date": "2025-11-28",
  "title": "俄称在红军城继续推进 乌称在多方向击退俄军进攻",
  "content": "俄罗斯国防部27日称，俄军在苏梅、哈尔科夫等多个方向打击乌军，并在顿涅茨克地区又控制一个居民点。在红军城（乌称波克罗夫斯克），俄军继续在多个区域推进，并击退乌军多次突围行动。乌克兰方面同一天称，乌军在波克罗夫斯克、亚历山德里夫斯克等方向击退俄军数十次进攻，打击俄军人员和武器装备集中区、无人机控制点等目标，并击落俄军200多架无人机。普京表示俄军在各战线态势积极 推进速度显著提升俄罗斯总统普京27日在访问吉尔吉斯斯坦时表示，俄军在特别军事行动各战线均保持积极态势，推进速度显著提升。普京表示，俄方总体上认为，美国提出的乌克兰问题和平计划可以作为未来协议的基础。 “北溪”爆炸案一嫌疑人被引渡至德国此外，德国联邦检察院27日证实，一名此前羁押在意大利的“北溪”天然气管道爆炸案乌克兰籍嫌疑人当天被引渡至德国。",
  "sourceUrl": "https://cn.govopendata.com/xinwenlianbo/20251128",
  "scrapedAt": "2025-11-29T09:45:10.801Z"
}